yufrosine/__init__.py
yufrosine/compnay_sentiment_caller.py
yufrosine/main.py
yufrosine/simple_single_stock_sentiment_analyzer.py
yufrosine/article_fetcher/News_api_spaCy_fetcher.py
yufrosine/article_fetcher/__init__.py
yufrosine/article_fetcher/base.py
yufrosine/sentiment_analyzer/__init__.py
yufrosine/sentiment_analyzer/base.py
yufrosine/sentiment_analyzer/util.py
yufrosine/sentiment_analyzer/vader_analyzer.py
yufrosine-0.1.dist-info/METADATA
yufrosine-0.1.dist-info/WHEEL
yufrosine-0.1.dist-info/top_level.txt
yufrosine-0.1.dist-info/RECORD
