Metadata-Version: 2.1
Name: yufrosine
Version: 0.1
Summary: lightweight sentiment analysis tool for financial news
Home-page: https://github.com/websmartprint/Sentiment-Analyzer
Author: Daniel Popa
Requires-Python: >=3.8
Requires-Dist: spacy
Requires-Dist: pandas
Requires-Dist: vaderSentiment
Requires-Dist: newsapi-python
